{
  "audiobook.aiVoice": "AI ನಿರೂಪಣೆ ({provider})",
  "audiobook.badge": "ಆಡಿಯೊಬುಕ್",
  "audiobook.buy": "ಆಡಿಯೊ ಪುಸ್ತಕವನ್ನು ಖರೀದಿಸಿ",
  "audiobook.create": "ಆಡಿಯೊ ಪುಸ್ತಕವನ್ನು ರಚಿಸಿ",
  "audiobook.discoveryTitle": "ಆಡಿಯೊ ಪುಸ್ತಕಗಳು",
  "audiobook.downloadFailed": "ಡೌನ್‌ಲೋಡ್ ವಿಫಲವಾಗಿದೆ",
  "audiobook.downloadFailedStatus": "ಡೌನ್‌ಲೋಡ್ ವಿಫಲವಾಗಿದೆ ({status})",
  "audiobook.downloadOffline": "ಆಫ್‌ಲೈನ್‌ಗಾಗಿ ಡೌನ್‌ಲೋಡ್ ಮಾಡಿ",
  "audiobook.downloading": "ಡೌನ್‌ಲೋಡ್ ಆಗುತ್ತಿದೆ…",
  "audiobook.offlineUnsupported": "ಈ ಬ್ರೌಸರ್‌ನಲ್ಲಿ ಆಫ್‌ಲೈನ್ ಸಂಗ್ರಹಣೆ ಲಭ್ಯವಿಲ್ಲ.",
  "audiobook.freePreview": "ಉಚಿತ ಪೂರ್ವವೀಕ್ಷಣೆ",
  "audiobook.freePreviewHelp": "ಉಚಿತವಾಗಿ ಕೇಳಬಹುದಾದ ಆರಂಭಿಕ ಅಧ್ಯಾಯಗಳ ಸಂಖ್ಯೆ.",
  "audiobook.externalUrl": "ಬಾಹ್ಯ ಆಡಿಯೊ ಲಿಂಕ್",
  "audiobook.externalUrlHelp": "ಅಥವಾ ಬಾಹ್ಯ ಆಡಿಯೊ ಫೈಲ್‌ಗೆ ಲಿಂಕ್ ಮಾಡಿ (ಉಚಿತ / ಸಾರ್ವಜನಿಕ-ಡೊಮೇನ್ ಆವೃತ್ತಿಗಳು ಮಾತ್ರ).",
  "audiobook.fullBook": "ಪೂರ್ಣ-ಪುಸ್ತಕ ಫೈಲ್",
  "audiobook.listen": "ಆಡಿಯೊ ಪುಸ್ತಕವನ್ನು ಕೇಳಿ",
  "audiobook.listenExternal": "ಬಾಹ್ಯ ಸೈಟ್‌ನಲ್ಲಿ ಕೇಳಿ",
  "audiobook.manage": "ಆಡಿಯೊ ಪುಸ್ತಕ",
  "audiobook.narratedBy": "{names} ನಿರೂಪಿಸಿದ್ದಾರೆ",
  "audiobook.perChapter": "ಪ್ರತಿ-ಅಧ್ಯಾಯ ನಿರೂಪಣೆ",
  "audiobook.pricing": "ಆಡಿಯೊ ಪುಸ್ತಕ ಬೆಲೆ ನಿಗದಿ",
  "audiobook.purchaseMode": "ಖರೀದಿ ವಿಧಾನ",
  "audiobook.purchaseMode.bundle": "ಕಥೆಯೊಂದಿಗೆ ಬಂಡಲ್",
  "audiobook.purchaseMode.full": "ಪೂರ್ಣ ಆಡಿಯೊ ಪುಸ್ತಕ",
  "audiobook.purchaseMode.perChapter": "ಪ್ರತಿ ಅಧ್ಯಾಯ",
  "audiobook.removeOffline": "ಡೌನ್‌ಲೋಡ್ ತೆಗೆದುಹಾಕಿ",
  "audiobook.split": "ಆದಾಯ ಹಂಚಿಕೆ",
  "audiobook.split.author": "ಲೇಖಕ",
  "audiobook.splitMustTotal": "ಆದಾಯ ಹಂಚಿಕೆ ಒಟ್ಟು 100% ಆಗಿರಬೇಕು.",
  "audiobook.splitHelp": "ಪ್ರತಿ ಸ್ವೀಕರಿಸುವವರಿಗೆ ಸೃಷ್ಟಿಕರ್ತ ಪಾವತಿಯ ಪಾಲು. ಒಟ್ಟು 100% ಆಗಿರಬೇಕು. ಪಾಲನ್ನು ಪಡೆಯಲು ನಿರೂಪಕರು Stripe ಪಾವತಿಗಳನ್ನು ಕಾನ್ಫಿಗರ್ ಮಾಡಬೇಕು.",
  "audiobook.team.title": "ಆಡಿಯೊ ಪುಸ್ತಕ ತಂಡ",
  "audiobook.team.managers": "ನಿರ್ವಾಹಕರು",
  "audiobook.team.noManagers": "ಇನ್ನೂ ಯಾವುದೇ ನಿರ್ವಾಹಕರಿಲ್ಲ.",
  "audiobook.team.voiceActors": "ಧ್ವನಿ ಕಲಾವಿದರು",
  "audiobook.team.noVoiceActors": "ಇನ್ನೂ ಯಾವುದೇ ಧ್ವನಿ ಕಲಾವಿದರಿಲ್ಲ.",
  "audiobook.team.inviteHeading": "ತಂಡದ ಸದಸ್ಯರನ್ನು ಆಹ್ವಾನಿಸಿ",
  "audiobook.team.role.manager": "ನಿರ್ವಾಹಕ",
  "audiobook.team.role.voiceActor": "ಧ್ವನಿ ಕಲಾವಿದ",
  "audiobook.team.searchUser": "ಬಳಕೆದಾರರನ್ನು ಹುಡುಕಿ…",
  "audiobook.team.party.organization": "ಸಂಸ್ಥೆ",
  "audiobook.team.selectOrg": "ಒಂದು ಸಂಸ್ಥೆಯನ್ನು ಆಯ್ಕೆಮಾಡಿ…",
  "audiobook.team.splitPlaceholder": "ಆದಾಯ ಪಾಲು % (ಐಚ್ಛಿಕ)",
  "audiobook.team.sendInvite": "ಆಹ್ವಾನ ಕಳುಹಿಸಿ",
  "audiobook.team.splitHelp": "ಪ್ರಸ್ತಾವಿತ ಆದಾಯ ಪಾಲನ್ನು ಆಹ್ವಾನಿತರಿಗೆ ಅವರ ಪಾತ್ರ ಒಪ್ಪಂದದಲ್ಲಿ ತೋರಿಸಲಾಗುತ್ತದೆ. ಅವರು ಸೇರಿ Stripe ಪಾವತಿಗಳನ್ನು ಕಾನ್ಫಿಗರ್ ಮಾಡಿದ ನಂತರ ಆಡಿಯೊ ಪುಸ್ತಕ ಬೆಲೆ ನಿಗದಿ ವಿಭಾಗದಲ್ಲಿ ನಿಜವಾದ ಹಂಚಿಕೆಯನ್ನು ಹೊಂದಿಸಿ.",
  "audiobook.team.invitesHeading": "ಆಡಿಯೊ ಪುಸ್ತಕ ಆಹ್ವಾನಗಳು",
  "audiobook.team.agreement.title": "ಪಾತ್ರ ಒಪ್ಪಂದ",
  "audiobook.team.agreement.error": "ನಿಮ್ಮ ಒಪ್ಪಿಗೆಯನ್ನು ದಾಖಲಿಸಲು ಸಾಧ್ಯವಾಗಲಿಲ್ಲ. ದಯವಿಟ್ಟು ಮತ್ತೆ ಪ್ರಯತ್ನಿಸಿ.",
  "audiobook.team.managedHeading": "ನೀವು ನಿರ್ವಹಿಸುವ ಆಡಿಯೊ ಪುಸ್ತಕಗಳು",
  "audiobook.team.you": "ನೀವು",
  "audiobook.manager.intro": "ಈ ಆಡಿಯೊ ಪುಸ್ತಕದ ನಿರ್ಮಾಣವನ್ನು ನೀವು ನಿರ್ವಹಿಸುತ್ತೀರಿ. ಬೆಲೆ ನಿಗದಿ, ಆದಾಯ ಹಂಚಿಕೆ ಮತ್ತು ತಂಡವನ್ನು ಮಾಲೀಕರು ನಿರ್ವಹಿಸುತ್ತಾರೆ.",
  "audiobook.stats.title": "ಆಲಿಸುವಿಕೆ ವಿಶ್ಲೇಷಣೆ",
  "audiobook.stats.summary": "{listeners, plural, one {# ಕೇಳುಗ} other {# ಕೇಳುಗರು}} ಮೂಲಕ {minutes} ನಿಮಿಷ ಆಲಿಸಲಾಗಿದೆ",
  "audiobook.stats.dayTooltip": "{date}: {minutes} ನಿಮಿಷ ಆಲಿಸಲಾಗಿದೆ, {sessions} ಸೆಷನ್‌ಗಳು"
}
